LICENSE.txt
MANIFEST.in
README.txt
setup.py
bin/grace
grace/__init__.py
grace/build.py
grace/cmdparse.py
grace/config.py
grace/create.py
grace/deploy.py
grace/doc.py
grace/error.py
grace/lint.py
grace/management.py
grace/task.py
grace/testit.py
grace/update.py
grace/upload.py
grace/utils.py
grace/zipit.py
grace.egg-info/PKG-INFO
grace.egg-info/SOURCES.txt
grace.egg-info/dependency_links.txt
grace.egg-info/requires.txt
grace.egg-info/top_level.txt
grace/assets/grace.cfg
grace/assets/manage.py
grace/py27/__init__.py
grace/py27/cssmin.py
grace/py27/pyjsdoc.py
grace/py27/slimit/__init__.py
grace/py27/slimit/ast.py
grace/py27/slimit/lexer.py
grace/py27/slimit/lextab.py
grace/py27/slimit/mangler.py
grace/py27/slimit/minifier.py
grace/py27/slimit/parser.py
grace/py27/slimit/scope.py
grace/py27/slimit/unicode_chars.py
grace/py27/slimit/yacctab.py
grace/py27/slimit/tests/__init__.py
grace/py27/slimit/tests/test_cmd.py
grace/py27/slimit/tests/test_ecmavisitor.py
grace/py27/slimit/tests/test_lexer.py
grace/py27/slimit/tests/test_mangler.py
grace/py27/slimit/tests/test_minifier.py
grace/py27/slimit/tests/test_nodevisitor.py
grace/py27/slimit/tests/test_parser.py
grace/py27/slimit/visitors/__init__.py
grace/py27/slimit/visitors/ecmavisitor.py
grace/py27/slimit/visitors/minvisitor.py
grace/py27/slimit/visitors/nodevisitor.py
grace/py27/slimit/visitors/scopevisitor.py