Metadata-Version: 1.1
Name: grace
Version: 0.5.7
Summary: A tool to simplify JavaScript development.
Home-page: https://github.com/mdiener/grace
Author: Michael Diener
Author-email: michael@webdiener.ch
License: LICENSE.txt
Keywords: toolchain javascript dizmo js buildtool
Platform: UNKNOWN
Classifier: Topic :: Software Development :: Build Tools
Classifier: Programming Language :: Python :: 2.7
Classifier: Programming Language :: Python :: 3.5
Classifier: Programming Language :: JavaScript
Classifier: Operating System :: OS Independent
Classifier: Natural Language :: English
Classifier: License :: OSI Approved :: GNU General Public License v3 or later (GPLv3+)
Classifier: Intended Audience :: Developers
Classifier: Environment :: Console
